{
  "subtitles": [
    {
      "number": "﻿1",
      "stopTime": "00:00:06,340",
      "startTime": "00:00:03,280",
      "text": "第一課　接吻二三事"
    },
    {
      "number": "2",
      "stopTime": "00:00:09,280",
      "startTime": "00:00:06,760",
      "text": "接吻是人生中不可避免的行為"
    },
    {
      "number": "3",
      "stopTime": "00:00:14,080",
      "startTime": "00:00:09,760",
      "text": "在某些情況下　不管你多不願意　你都一定要接吻"
    },
    {
      "number": "4",
      "stopTime": "00:00:17,000",
      "startTime": "00:00:14,080",
      "text": "不管是基於父母之間的親情　朋友之間的友情"
    },
    {
      "number": "5",
      "stopTime": "00:00:18,680",
      "startTime": "00:00:17,000",
      "text": "或基於男女朋友之間的愛情"
    },
    {
      "number": "6",
      "stopTime": "00:00:21,480",
      "startTime": "00:00:18,680",
      "text": "接吻是你必需了解"
    },
    {
      "number": "7",
      "stopTime": "00:00:23,880",
      "startTime": "00:00:21,480",
      "text": "必需學習　必需實踐的事"
    },
    {
      "number": "8",
      "stopTime": "00:00:25,200",
      "startTime": "00:00:23,880",
      "text": "你好　我是Jessica C"
    },
    {
      "number": "9",
      "stopTime": "00:00:28,080",
      "startTime": "00:00:25,200",
      "text": "你們正在觀看 Kissing Lecture 第一季"
    },
    {
      "number": "10",
      "stopTime": "00:00:30,600",
      "startTime": "00:00:28,080",
      "text": "在這一季的學習影片中　你會學到有關接吻的基本知識"
    },
    {
      "number": "11",
      "stopTime": "00:00:32,800",
      "startTime": "00:00:30,600",
      "text": "以及如何能更專業地和伴侶接吻"
    },
    {
      "number": "12",
      "stopTime": "00:00:35,360",
      "startTime": "00:00:32,800",
      "text": "不管這是你的初吻"
    },
    {
      "number": "13",
      "stopTime": "00:00:38,800",
      "startTime": "00:00:35,360",
      "text": "或是已有一定的接吻經驗　都會在這視頻中得益不少"
    },
    {
      "number": "14",
      "stopTime": "00:00:42,200",
      "startTime": "00:00:39,240",
      "text": "第一節　接吻基礎"
    },
    {
      "number": "15",
      "stopTime": "00:00:46,200",
      "startTime": "00:00:44,240",
      "text": "在這課堂裡　你將會學到接吻的文化"
    },
    {
      "number": "16",
      "stopTime": "00:00:48,200",
      "startTime": "00:00:46,200",
      "text": "以及基本的接吻技巧"
    },
    {
      "number": "17",
      "stopTime": "00:00:52,120",
      "startTime": "00:00:48,200",
      "text": "應用於社交禮儀上的接吻技巧　以及如何親吻面頰　慢慢觀賞"
    },
    {
      "number": "18",
      "stopTime": "00:00:54,000",
      "startTime": "00:00:52,120",
      "text": "接吻的各種用途"
    },
    {
      "number": "19",
      "stopTime": "00:00:59,680",
      "startTime": "00:00:54,000",
      "text": "吻可以用作表示對別人的欣賞　尊重　讚美"
    },
    {
      "number": "20",
      "stopTime": "00:01:01,100",
      "startTime": "00:00:59,680",
      "text": "也是愛和友情的一種表達方式"
    },
    {
      "number": "21",
      "stopTime": "00:01:03,520",
      "startTime": "00:01:01,520",
      "text": "接吻並不是一種世界通行的文化"
    },
    {
      "number": "22",
      "stopTime": "00:01:06,320",
      "startTime": "00:01:03,520",
      "text": "有些非洲部落沒有接吻文化"
    },
    {
      "number": "23",
      "stopTime": "00:01:12,600",
      "startTime": "00:01:10,520",
      "text": "根據一些醫學文獻"
    },
    {
      "number": "24",
      "stopTime": "00:01:18,040",
      "startTime": "00:01:12,600",
      "text": "接吻可以幫助放鬆　降低膽固醇及血壓"
    },
    {
      "number": "25",
      "stopTime": "00:01:21,280",
      "startTime": "00:01:18,040",
      "text": "故此　接吻是有益及有其療效"
    },
    {
      "number": "26",
      "stopTime": "00:01:23,800",
      "startTime": "00:01:21,280",
      "text": "接吻源自哪裡"
    },
    {
      "number": "27",
      "stopTime": "00:01:27,240",
      "startTime": "00:01:25,080",
      "text": "根據人類學家的研究"
    },
    {
      "number": "28",
      "stopTime": "00:01:30,480",
      "startTime": "00:01:27,240",
      "text": "古印度是接吻的發源地"
    },
    {
      "number": "29",
      "stopTime": "00:01:36,320",
      "startTime": "00:01:30,480",
      "text": "從印度的雕塑　也是首個在雕塑中呈現接吻的文化中"
    },
    {
      "number": "30",
      "stopTime": "00:01:41,640",
      "startTime": "00:01:36,320",
      "text": "二人的嘴唇緊貼　代表練氣呼吸"
    },
    {
      "number": "31",
      "stopTime": "00:01:43,120",
      "startTime": "00:01:41,640",
      "text": "人類學家也認為"
    },
    {
      "number": "32",
      "stopTime": "00:01:46,800",
      "startTime": "00:01:43,120",
      "text": "在古時　接吻的行為必定發生在母親和孩子之間"
    },
    {
      "number": "33",
      "stopTime": "00:01:48,520",
      "startTime": "00:01:46,800",
      "text": "作為傳送食物之用"
    },
    {
      "number": "34",
      "stopTime": "00:01:51,240",
      "startTime": "00:01:48,720",
      "text": "與性沒有關係的接吻"
    },
    {
      "number": "35",
      "stopTime": "00:01:55,920",
      "startTime": "00:01:52,520",
      "text": "飛吻　雙唇並沒有緊貼"
    },
    {
      "number": "36",
      "stopTime": "00:01:59,600",
      "startTime": "00:01:55,920",
      "text": "利用手掌親吻　並做吹氣動作"
    },
    {
      "number": "37",
      "stopTime": "00:02:02,880",
      "startTime": "00:02:00,560",
      "text": "明星經常在觀眾面前飛吻"
    },
    {
      "number": "38",
      "stopTime": "00:02:06,080",
      "startTime": "00:02:02,880",
      "text": "此舉或用以感激粉絲　或用以擺出可愛而性感的姿勢"
    },
    {
      "number": "39",
      "stopTime": "00:02:07,800",
      "startTime": "00:02:06,840",
      "text": "婚禮上的親吻"
    },
    {
      "number": "40",
      "stopTime": "00:02:13,000",
      "startTime": "00:02:07,800",
      "text": "在婚禮儀式後　新郎和新娘會親吻對方　以代表永結同心"
    },
    {
      "number": "41",
      "stopTime": "00:02:16,320",
      "startTime": "00:02:13,000",
      "text": "通常一個人親吻一件物件　代表他很喜歡"
    },
    {
      "number": "42",
      "stopTime": "00:02:18,000",
      "startTime": "00:02:16,320",
      "text": "或尊重該物件"
    },
    {
      "number": "43",
      "stopTime": "00:02:19,920",
      "startTime": "00:02:18,000",
      "text": "例如　聖經及戒指"
    },
    {
      "number": "44",
      "stopTime": "00:02:24,120",
      "startTime": "00:02:22,760",
      "text": "愛斯基摩式接吻"
    },
    {
      "number": "45",
      "stopTime": "00:02:28,920",
      "startTime": "00:02:24,720",
      "text": "由於居住的地方非常寒冷　他們害怕親吻時嘴唇黏在一起"
    },
    {
      "number": "46",
      "stopTime": "00:02:31,400",
      "startTime": "00:02:29,000",
      "text": "所以只會磨擦鼻子"
    },
    {
      "number": "47",
      "stopTime": "00:02:33,520",
      "startTime": "00:02:32,240",
      "text": "以示歡迎"
    },
    {
      "number": "48",
      "stopTime": "00:02:35,840",
      "startTime": "00:02:34,000",
      "text": "不同國家的接吻文化"
    },
    {
      "number": "49",
      "stopTime": "00:02:39,920",
      "startTime": "00:02:36,800",
      "text": "很多文化　均以親吻面頰打招呼"
    },
    {
      "number": "50",
      "stopTime": "00:02:42,160",
      "startTime": "00:02:39,920",
      "text": "每個國家都有自己獨特的親吻文化"
    },
    {
      "number": "51",
      "stopTime": "00:02:44,800",
      "startTime": "00:02:42,800",
      "text": "在斯洛文尼亞　塞爾維亞"
    },
    {
      "number": "52",
      "stopTime": "00:02:47,480",
      "startTime": "00:02:44,800",
      "text": "波斯尼亞　馬其頓"
    },
    {
      "number": "53",
      "stopTime": "00:02:50,080",
      "startTime": "00:02:47,480",
      "text": "蒙特尼哥羅　荷蘭及埃及"
    },
    {
      "number": "54",
      "stopTime": "00:02:53,680",
      "startTime": "00:02:50,080",
      "text": "通常均會在雙頰吻三次"
    },
    {
      "number": "55",
      "stopTime": "00:02:57,920",
      "startTime": "00:02:55,400",
      "text": "意大利一般於打招呼時　親吻兩次"
    },
    {
      "number": "56",
      "stopTime": "00:03:03,480",
      "startTime": "00:03:00,200",
      "text": "在墨西哥和比利時　則只需親吻一次面頰"
    },
    {
      "number": "57",
      "stopTime": "00:03:09,240",
      "startTime": "00:03:06,640",
      "text": "在法國文化中　有多種不同的面頰親吻方式"
    },
    {
      "number": "58",
      "stopTime": "00:03:10,560",
      "startTime": "00:03:09,240",
      "text": "視乎不同的地區而定"
    },
    {
      "number": "59",
      "stopTime": "00:03:13,400",
      "startTime": "00:03:10,560",
      "text": "一般來說　面頰接吻兩次於全國內比較普遍"
    },
    {
      "number": "60",
      "stopTime": "00:03:18,400",
      "startTime": "00:03:15,720",
      "text": "德國人只會與熟悉的人親吻"
    },
    {
      "number": "61",
      "stopTime": "00:03:20,840",
      "startTime": "00:03:18,400",
      "text": "絕大部分時間　均只會握手"
    },
    {
      "number": "62",
      "stopTime": "00:03:26,280",
      "startTime": "00:03:22,760",
      "text": "在英國　點頭有時會代替握手"
    },
    {
      "number": "63",
      "stopTime": "00:03:40,000",
      "startTime": "00:03:36,480",
      "text": "並不是每一種接吻　均是與情愛有關"
    },
    {
      "number": "64",
      "stopTime": "00:03:42,120",
      "startTime": "00:03:40,000",
      "text": "在部分國家　如歐美地區的國家"
    },
    {
      "number": "65",
      "stopTime": "00:03:43,640",
      "startTime": "00:03:42,120",
      "text": "接吻是一種社交禮儀"
    },
    {
      "number": "66",
      "stopTime": "00:03:47,680",
      "startTime": "00:03:44,440",
      "text": "親吻手背代表尊重"
    },
    {
      "number": "67",
      "stopTime": "00:03:51,760",
      "startTime": "00:03:47,880",
      "text": "親吻額頭代表深厚的友情"
    },
    {
      "number": "68",
      "stopTime": "00:03:56,040",
      "startTime": "00:03:53,200",
      "text": "親吻面頰代表深情"
    },
    {
      "number": "69",
      "stopTime": "00:04:00,760",
      "startTime": "00:03:57,520",
      "text": "親吻邊代表愛情"
    },
    {
      "number": "70",
      "stopTime": "00:04:05,400",
      "startTime": "00:04:02,000",
      "text": "親吻眼簾代表崇拜"
    },
    {
      "number": "71",
      "stopTime": "00:04:10,720",
      "startTime": "00:04:07,000",
      "text": "親吻手腕代表渴求"
    },
    {
      "number": "72",
      "stopTime": "00:04:16,240",
      "startTime": "00:04:12,320",
      "text": "第二節　Cheek Kiss 親吻面頰"
    },
    {
      "number": "73",
      "stopTime": "00:04:19,800",
      "startTime": "00:04:17,000",
      "text": "親吻面頰在西方世界非常普遍"
    },
    {
      "number": "74",
      "stopTime": "00:04:23,760",
      "startTime": "00:04:19,800",
      "text": "你在現實生活中或電影裡　肯定見過不少"
    },
    {
      "number": "75",
      "stopTime": "00:04:27,600",
      "startTime": "00:04:23,760",
      "text": "但當你真正親吻面頰時候　卻依然會感到尷尬"
    },
    {
      "number": "76",
      "stopTime": "00:04:30,600",
      "startTime": "00:04:27,600",
      "text": "跟著以下的步驟　你可以正確地親吻面頰"
    },
    {
      "number": "77",
      "stopTime": "00:04:34,120",
      "startTime": "00:04:30,600",
      "text": "第一步　選擇正確的方向"
    },
    {
      "number": "78",
      "stopTime": "00:04:39,280",
      "startTime": "00:04:36,160",
      "text": "身體移向左邊　來親吻別人的右邊面頰"
    },
    {
      "number": "79",
      "stopTime": "00:04:41,000",
      "startTime": "00:04:39,280",
      "text": "如果你是被動的一方"
    },
    {
      "number": "80",
      "stopTime": "00:04:43,280",
      "startTime": "00:04:41,000",
      "text": "請展示你的右邊臉頰"
    },
    {
      "number": "81",
      "stopTime": "00:04:47,680",
      "startTime": "00:04:44,400",
      "text": "你得記住　被動的一方在右邊　主動的一方在左邊"
    },
    {
      "number": "82",
      "stopTime": "00:04:50,640",
      "startTime": "00:04:47,680",
      "text": "在某些國家　情況可能是相反"
    },
    {
      "number": "83",
      "stopTime": "00:04:54,540",
      "startTime": "00:04:50,640",
      "text": "若不小心碰撞鼻子　笑一笑就好　不用尷尬"
    },
    {
      "number": "84",
      "stopTime": "00:04:58,440",
      "startTime": "00:04:54,540",
      "text": "在大多數的情況下　親吻面頰不適用於男和男"
    },
    {
      "number": "85",
      "stopTime": "00:05:00,920",
      "startTime": "00:04:58,440",
      "text": "男士一般只是擁抱或握手"
    },
    {
      "number": "86",
      "stopTime": "00:05:03,360",
      "startTime": "00:05:01,000",
      "text": "親吻面頰比較適合男和女　或女和女之間"
    },
    {
      "number": "87",
      "stopTime": "00:05:06,520",
      "startTime": "00:05:03,360",
      "text": "第二步　保持平衡"
    },
    {
      "number": "88",
      "stopTime": "00:05:10,080",
      "startTime": "00:05:06,520",
      "text": "把你的右手放在別人的左肩　來保持平衡"
    },
    {
      "number": "89",
      "stopTime": "00:05:11,640",
      "startTime": "00:05:10,080",
      "text": "以免失去平衡　墮進對方懷中"
    },
    {
      "number": "90",
      "stopTime": "00:05:16,400",
      "startTime": "00:05:11,640",
      "text": "同時也能表達　你對對方的友好和熱情"
    },
    {
      "number": "91",
      "stopTime": "00:05:19,560",
      "startTime": "00:05:16,400",
      "text": "第三步　抬起你的面頰"
    },
    {
      "number": "92",
      "stopTime": "00:05:23,040",
      "startTime": "00:05:19,560",
      "text": "以 45 度角的方向　微微抬起你的面頰"
    },
    {
      "number": "93",
      "stopTime": "00:05:25,800",
      "startTime": "00:05:23,040",
      "text": "你也可以和對方的面頰　保持一定距離"
    },
    {
      "number": "94",
      "stopTime": "00:05:27,960",
      "startTime": "00:05:25,800",
      "text": "這亦是凌空親吻的一種"
    },
    {
      "number": "95",
      "stopTime": "00:05:33,000",
      "startTime": "00:05:27,960",
      "text": "第四步　嘟起雙唇　發出 muah 的聲音"
    },
    {
      "number": "96",
      "stopTime": "00:05:35,320",
      "startTime": "00:05:33,000",
      "text": "嘟起雙唇　做出接吻的樣子"
    },
    {
      "number": "97",
      "stopTime": "00:05:38,440",
      "startTime": "00:05:35,320",
      "text": "並輕輕的發出 muah 的聲音"
    },
    {
      "number": "98",
      "stopTime": "00:05:41,160",
      "startTime": "00:05:38,440",
      "text": "這也代表著　你對親吻面頰的熱情"
    },
    {
      "number": "99",
      "stopTime": "00:05:43,120",
      "startTime": "00:05:41,160",
      "text": "當然　不要發出太大的聲音"
    },
    {
      "number": "100",
      "stopTime": "00:05:45,000",
      "startTime": "00:05:43,120",
      "text": "只讓對方聽見即可"
    },
    {
      "number": "101",
      "stopTime": "00:05:47,840",
      "startTime": "00:05:45,000",
      "text": "第五步　於另一面頰重複"
    },
    {
      "number": "102",
      "stopTime": "00:05:52,920",
      "startTime": "00:05:48,440",
      "text": "你可在左右面頰　重複數次"
    },
    {
      "number": "103",
      "stopTime": "00:05:54,800",
      "startTime": "00:05:53,000",
      "text": "部分法國人　會親吻面頰四遍"
    },
    {
      "number": "104",
      "stopTime": "00:05:57,000",
      "startTime": "00:05:54,800",
      "text": "在雙頰重覆數次"
    },
    {
      "number": "105",
      "stopTime": "00:06:00,000",
      "startTime": "00:05:57,000",
      "text": "在波蘭　一般會重覆親吻三遍"
    },
    {
      "number": "106",
      "stopTime": "00:06:03,400",
      "startTime": "00:06:00,000",
      "text": "先是左邊面頰　之後在右邊面頰重覆"
    },
    {
      "number": "107",
      "stopTime": "00:06:07,480",
      "startTime": "00:06:03,400",
      "text": "第六步　親吻雙頰後後退"
    },
    {
      "number": "108",
      "stopTime": "00:06:13,280",
      "startTime": "00:06:10,720",
      "text": "如果你不希望碰到別人的面頰"
    },
    {
      "number": "109",
      "stopTime": "00:06:15,240",
      "startTime": "00:06:13,280",
      "text": "你可凌空親吻"
    },
    {
      "number": "110",
      "stopTime": "00:06:18,160",
      "startTime": "00:06:15,240",
      "text": "步驟一樣　不碰到對方的面頰即可"
    },
    {
      "number": "111",
      "stopTime": "00:06:21,880",
      "startTime": "00:06:19,080",
      "text": "凌空親吻在西方世界　也是很流行"
    }
  ]
}